Metadata-Version: 1.0
Name: kafka-rest
Version: 0.0.12
Summary: Async client for Confluent's Kafka REST Proxy
Home-page: https://github.com/gamechanger/kafka-rest
Author: GameChanger
Author-email: travis@gc.io
License: UNKNOWN
Platform: UNKNOWN
